skyway_ndtrung/__init__.py
skyway_ndtrung/__main__.py
skyway_ndtrung/configs.py
skyway_ndtrung/db.py
skyway_ndtrung/nodemap.py
skyway_ndtrung/account/__init__.py
skyway_ndtrung/account/__main__.py
skyway_ndtrung/account/test.py
skyway_ndtrung/billing/__init__.py
skyway_ndtrung/billing/__main__.py
skyway_ndtrung/billing/check.py
skyway_ndtrung/billing/report.py
skyway_ndtrung/billing/service.py
skyway_ndtrung/cli/__init__.py
skyway_ndtrung/cli/__main__.py
skyway_ndtrung/cli/users.py
skyway_ndtrung/cloud/__init__.py
skyway_ndtrung/cloud/__main__.py
skyway_ndtrung/cloud/aws.py
skyway_ndtrung/cloud/gcp.py
skyway_ndtrung/cloud/service.py
skyway_ndtrung/misc/db_test.py
skyway_ndtrung/misc/nodes.py
skyway_ndtrung/misc/sendmail.py
skyway_ndtrung/misc/update_firewall_ips.py
skyway_ndtrung/service/__init__.py
skyway_ndtrung/service/__main__.py
skyway_ndtrung/service/daemon.py
skyway_ndtrung/slurm/__init__.py
skyway_ndtrung/slurm/__main__.py
skyway_ndtrung/watcher/__init__.py
skyway_ndtrung/watcher/service.py
Skyway_maroon-1.0.0.dist-info/LICENSE
Skyway_maroon-1.0.0.dist-info/METADATA
Skyway_maroon-1.0.0.dist-info/WHEEL
Skyway_maroon-1.0.0.dist-info/top_level.txt
Skyway_maroon-1.0.0.dist-info/RECORD
