Metadata-Version: 2.1
Name: Skyway-maroon
Version: 1.0.0
Summary: Skyway -- a python package for bridging on-premises and cloud resources
Author-email: Yuxing Peng <yuxing@uchicago.edu>, "H. Birali Runesha" <runesha@uchicago.edu>, Trung Nguyen <ndtrung@uchicago.edu>
Project-URL: Homepage, https://cloud-skyway.rcc.uchicago.edu/
Classifier: Programming Language :: Python :: 3
Classifier: License :: OSI Approved :: BSD License
Classifier: Operating System :: OS Independent
Requires-Python: >=3.7
License-File: LICENSE
